{"metadata":{"language":"bulgarian","has_partitions":false,"min_word_length":4,"max_word_length":9,"min_chars":8},"wordlengths":{"4":["агол","азил","алги","алея","анти","атол","атом","ајде","база","бара","бело","бира","биро","блок","боец","борд","бори","брак","бран","брег","брзо","брои","бряг","бука","бунт","бута","бърз","бюро","бяло","важи","вест","вето","вече","веќе","взет","види","виза","влак","влез","внос","вода","води","воен","воля","врат","врти","врши","връх","втор","въже","глад","глас","гнил","гора","горе","град","грип","гръб","грък","дава","даде","дата","дваж","дели","дете","дето","диво","диша","дише","днес","дожд","долг","долж","дома","дори","дрво","држи","дроб","друг","дува","дума","дури","духа","дъжд","дълг","евро","език","елен","есен","жена","жълт","заем","збор","зема","земе","змия","знае","знак","зона","игра","идва","иден","идея","имот","иска","исто","итно","йена","каде","каже","како","кани","като","кафе","клуб","кога","кожа","копа","кора","коса","кост","край","крак","крај","крие","кръв","купа","купи","курд","кусо","куче","куќа","къде","късо","къща","кюрд","лаже","лайф","лајв","лево","лежи","лета","лети","лето","лига","лист","лице","лошо","луна","луѓе","лъже","ляво","лято","маже","март","маса","маст","меко","месо","миля","мина","мито","млад","може","мора","море","мост","мраз","нали","небе","небо","неин","нели","нема","нето","нефт","ниво","низш","нима","нито","ниту","нищо","ново","нога","нокт","носи","нуди","няма","общо","овде","оган","огън","онзи","оној","осми","пада","пакт","папа","пара","парк","пати","паѓа","перо","пети","пеша","пиво","пише","план","плод","плус","плюе","плюс","поле","поне","пост","прав","прах","прес","прът","пъти","рака","ранг","рано","раст","реже","река","рече","риба","риск","роля","ръка","ръст","саем","сака","само","свет","свой","свят","сега","седи","село","семе","сиво","сида","сила","сиот","слаб","след","смее","смрт","снег","сняг","спад","спие","спор","спре","сред","срце","стап","стар","стил","стои","суво","суди","сума","сухо","съди","също","така","таму","тапо","твой","твој","тело","тема","тест","тече","трае","трет","трие","триж","трка","труд","тука","тъпо","тяло","убит","увоз","удар","удря","указ","уста","утре","учен","уште","фаза","факт","филм","фино","фонд","фрла","хала","ходи","хора","храм","цвет","цвят","цело","цена","црно","цяло","чака","чека","чело","чест","чете","чеша","чини","чист","чита","чичо","чрез","шанс","шија","шума","щета","ъгъл","южен","южно","яйце","ясен","ясно","јаде","јаже","јули","јуни"],"5":["агора","аквис","акула","акциз","аорта","април","арест","армия","астма","бавен","бавно","бадем","банка","баран","барем","басна","басня","бегло","белка","берза","билка","бисер","близо","близу","божиќ","бойно","болен","болно","бомба","борба","борса","брани","брише","броен","буква","булга","бураг","буџет","бързо","бърше","важен","важно","вајар","вежба","вечен","вечер","вечно","взема","вземе","взето","виден","видео","видно","визен","визно","визов","вирус","висок","влада","власт","влезе","влече","влиза","влияе","водач","воден","водещ","водно","воено","война","волја","вошка","војна","врата","врати","враќа","време","врска","връща","всеки","втори","вчера","вълна","върне","върти","върху","върши","въшка","вярва","газет","гласа","гледа","гнило","говор","голем","голям","горен","горно","града","гребе","греши","група","грчки","гърда","даден","данок","данък","датум","движи","двоен","дебат","денар","денем","денес","детал","динар","доаѓа","добар","добие","добро","добър","дойде","доказ","долар","долго","долен","должи","долно","домат","доцна","дојде","дрога","друго","дълго","дължи","дълъг","дърво","държи","дърпа","еднаш","езеро","жалба","жален","жално","желба","живее","живот","жител","жртва","заден","задно","закон","заоди","запад","засее","затоа","захар","здава","здаде","здржи","зелен","земен","земно","зимно","змија","знаме","значи","играе","идеја","избор","извоз","извън","износ","изоди","изток","изход","исток","исход","казан","казва","камен","камък","канал","карта","клане","клима","книга","колко","колку","копае","корен","коска","кочан","краен","криза","крило","късно","ладно","лажно","лекар","лесен","лесно","летен","летно","лидер","линия","липса","листа","личен","лично","лишен","лятно","магла","мазно","майка","майор","макар","малко","малку","малък","масов","мајка","мајор","медал","меден","медиа","медно","мерен","мерка","мерно","месец","место","метар","метър","миене","миење","милја","мирно","мисия","мисла","мисли","мисъл","младо","много","модел","моден","модно","можно","мокро","мокър","момче","мрежа","мртво","музей","музеј","мъгла","мярка","място","навън","надеж","наема","наеме","назад","наиде","налог","наоѓа","напор","народ","насее","наука","нафта","нация","начин","најде","негов","некој","немай","немир","нетно","нивен","никой","никој","ништо","нокът","нужда","нужен","нужно","някой","обаче","обект","обиде","облак","обмен","обука","оглед","одбор","оддел","однос","одѕив","океан","около","околу","опита","опише","опция","орган","освои","остро","остър","осуди","осъди","отбор","отдел","отзив","отпад","отсее","отсто","оцени","падне","пазар","пакет","памук","пасош","пеене","пеење","пепел","песен","песна","песок","петок","петти","петък","печат","писмо","плава","плата","плати","плаши","плаща","плаќа","плива","плови","плува","плука","повод","пожар","полет","полза","полно","помош","помощ","пооди","поред","посее","после","потег","потоа","почва","почит","почне","появи","прави","право","пране","праша","преку","прием","прост","птица","птичи","пункт","пушка","пълен","пълно","първи","пясък","радва","радио","разно","рамка","ранно","рачно","режим","решен","ризик","роден","родно","роман","руски","ръчно","самит","свето","свика","сврши","свято","сдава","сдаде","север","седми","седне","сезон","секој","сепак","серия","силен","силно","сирак","ситен","ситно","скала","скрие","слабо","следи","слово","служи","слуша","смени","сменя","смета","смрди","смърт","смята","собор","совет","сокак","сонце","соочи","сосед","спира","спорт","спъва","србин","среда","среща","срещу","сряда","става","стане","стапи","старо","стига","стока","стъпи","сцена","събор","съвет","съдия","сърце","съсед","тайна","такъв","тајна","тврди","тврдо","тежко","тежък","текст","темпо","тенко","терен","тесен","тесно","техен","тешко","тогаш","толку","топло","топол","топъл","точен","точно","трева","трети","турка","тънко","тънък","търси","тясно","убаво","убеди","убива","убиец","убито","уважи","увери","удари","удира","ужива","узнае","укаже","укине","улица","улога","умира","упати","упъти","успее","успех","устав","учење","финал","фирма","фокус","форма","форум","хайде","харта","хвали","храна","хрват","цивил","црква","чекор","ченал","ченъл","черен","черно","често","чесън","чешко","чисто","човек","чуден","чудно","шверц","шести","шеќер","широк","штета","ядрен","јавно","јазик","јасно","јајце","јужно","ќерка"],"6":["абанос","абонос","август","агенда","азбука","акциза","алианс","анализ","анемия","анкета","апсење","армија","ајкула","барано","барање","беглец","библия","бизнес","бизнис","биолог","ближен","ближно","близко","близок","близък","блиско","бойкот","бомбен","бојкот","бразда","брачен","брачно","брбори","броене","броење","бройка","бројка","бројно","бубрег","бъбрек","бъдеще","бюджет","вагина","валута","вандал","вгледа","вдишва","веднаш","веднъж","велико","верига","версия","верски","верува","весник","визово","викенд","високо","вклучи","включи","вкупно","владин","влажен","влажно","влакно","влијае","вместо","вмешан","водене","водещо","водење","военен","военно","возило","войник","војник","вреден","вредно","връзка","вулкан","възход","външен","външно","въпрос","газете","главен","главно","гладко","гладък","гласач","говори","година","големо","голямо","горене","горење","горски","господ","градус","гръцки","даване","давање","дадено","далеку","далече","двойно","двојно","дебата","дебело","декрет","делење","делови","детайл","детски","диалог","дишане","дишење","дневен","дневно","добави","добавя","добива","доврши","додава","додаде","додели","доземе","докаже","доклад","донася","донесе","допише","допрва","досега","достъп","дотрае","дочака","дочека","драска","древен","древно","дъщеря","елитен","елитно","есенно","женски","жертва","жесток","живина","жизнен","завиди","зависи","загива","загине","загуба","задава","зададе","задача","заделя","задржи","заедно","зазема","заземе","заиска","закана","закани","заканя","закрие","закупи","залавя","залага","залаже","залови","залъже","замена","замени","заменя","замине","замяна","заради","засака","засега","застои","затвор","затова","затрае","заходи","зачака","зачека","зачита","защита","защити","звезда","звучен","звучно","зграда","згреши","зелена","зелено","земено","зетски","зимско","златен","златно","знаење","знание","иднина","избега","избере","избира","избран","избяга","изврши","изглед","изгуби","издава","издаде","издржи","иззема","изземе","изкаже","изкупи","излаже","излезе","излиза","излъже","измама","измени","изменя","изнася","изнесе","изрази","изрече","изтече","изтича","изтрае","изходи","изчака","изјава","имотно","инакво","инаков","инакъв","инсайт","инсајт","искаже","искане","искупи","испита","истече","истина","истрае","исчека","кажува","камара","камион","клетва","климат","клучно","ключов","кодекс","колега","колено","колење","коляно","комора","корист","корпус","крайно","крајно","кромид","кружно","крупен","крупно","кръгло","купува","където","летище","линија","лишено","ловува","лъжлив","мандат","масакр","масово","мевлем","медено","медиум","мехлем","минало","минато","минута","мириса","мирише","мисија","митинг","млечен","млечно","мнение","можеби","мозаик","момент","момиче","мрачен","мрачно","мръсен","мръсно","музика","мъртво","наведе","наврши","надава","нададе","надвор","надева","надява","наедно","наивен","наивно","накаже","накупи","намали","намера","намери","намира","напада","напади","напише","напред","нареди","нарече","наруши","насила","насока","насред","настан","научен","научно","нација","начака","начало","начека","невино","негира","недела","некаде","нервен","нервно","нечист","нејзин","никаде","никога","никъде","новина","новост","някога","някъде","обвини","обзема","обземе","обилен","обилно","обичен","обично","област","обнова","обраќа","обръща","община","обясни","објект","оглави","огледа","оддава","оддаде","оддели","одигра","одложи","однесе","одобри","одреди","одрече","означи","околен","околна","околно","олесни","онаков","онакъв","онлайн","онлајн","опашка","описва","опитва","оправи","опрема","опфаќа","опција","оружје","оръжие","основа","особен","остави","остане","остров","осъден","осъжда","отвара","отваря","отвори","отдава","отдаде","отдели","откако","открит","откупи","отлага","отложи","отнася","отнесе","отреди","отрече","отрича","отстои","отфрли","офицер","оценка","очаква","панаир","папски","партия","парцел","пастор","патник","патува","пенсия","перење","период","печели","печене","печење","пишува","побара","победа","победи","повече","повеќе","повика","поводи","поврзе","поглед","погоди","погреб","подава","подаде","подели","подкуп","подред","подржи","познае","познат","поиска","покаже","покана","покани","покоен","покрай","покрие","ползва","полски","получи","помине","попита","попише","поради","порази","порака","пораст","порача","поръча","посака","посета","посети","посока","посочи","посред","постои","потене","потење","потрае","пофали","походи","почака","почека","почива","почине","појави","правда","правен","правец","правно","празен","празно","прачка","превоз","преден","предно","премин","пресее","преход","пречка","прието","пример","принос","приход","пробен","пробно","пролет","прооди","пророк","просек","просто","против","проучи","профит","процес","пръчка","пушене","пушење","пътник","пътува","работи","разход","ракета","растеж","реален","реално","ресурс","речник","решено","рилски","римски","родено","ромски","сабота","сведок","свещен","свърже","свърши","сграда","сгреши","сдържи","сезона","секаде","сектор","секция","селски","серија","сестра","сигнал","синџир","сираче","систем","славен","славно","слично","сложен","сложно","служба","слънце","сметка","смртно","смърди","собере","собира","собори","содржи","созема","соземе","сопруг","сосема","состав","состои","спадне","список","списък","според","спорно","справи","справя","спрема","спречи","спроти","спрямо","срамен","срамно","среден","средно","стапка","статус","статут","стачка","степен","стигне","стиска","страна","стреми","строго","струва","струја","студен","стъпва","стъпка","судење","судија","судско","събере","събира","събори","събота","съвсем","съпруг","сърбин","състав","състои","твърди","твърдо","театар","театър","текущо","тогава","топене","топење","трайно","трајно","тревна","трошок","трябва","турист","турски","турчин","търбух","търсен","убиено","уволни","ударен","ударно","ужасен","ужасно","уикенд","указва","улесни","уличен","улично","умение","уништи","упадне","управа","упътва","ураган","усилие","услужи","успева","успява","учение","учреди","фактор","филмов","финале","фински","фудбал","футбол","хагски","хвалба","хвърля","хектар","хероин","хладен","хладно","хубаво","царски","цветен","цветно","центар","център","цигара","цитира","църква","частен","частно","червей","червен","честен","честно","членка","шамија","широко","штрајк","ядрено","януари","ѕвезда","јаглен","јачина"],"7":["автобус","автопат","агенция","адвокат","аеробик","азорски","акропол","аксиома","активен","активно","албанец","албумин","алвеола","алдехид","алергия","алкохол","алчност","амбиция","анализа","анархия","анатема","анемија","анулира","арабски","арапски","арменец","армиски","атеизам","атеизъм","атентат","атински","балетно","бегалец","бегство","бедност","бернски","библија","бионика","близина","близост","блокира","болница","бомбено","борбено","босилек","ботаник","братски","бугарин","бърбори","бягство","важност","валкано","вдишува","веднага","вековен","вековно","верзија","вестник","вештина","взаемно","взаимно","виенски","виновен","виновно","вистина","вклучен","включва","включен","владино","влегува","влизане","влияние","вмешано","водечки","водејќи","водство","воздржи","возраст","востане","вработи","враќање","врховен","врховно","връщане","вторник","въвежда","въглища","възлезе","възраст","въстане","гасовод","генерал","геноцид","гласање","гласува","гледане","гледање","годишен","годишно","градски","граната","граница","давачка","далечен","далечно","даночен","даночно","данъчен","данъчно","двапати","движење","девојка","делегат","деление","деловен","делумен","делумно","десятка","детство","дефицит","дејство","дијалог","длабоко","дневник","доближи","довежда","доверба","доверие","довземе","доволен","доволно","довърши","догледа","договор","дозвола","доказва","доколку","должина","домакин","домашен","домашна","домашно","домаќин","донесен","допадне","дописва","доплаща","доплаќа","дослужи","достави","доставя","достига","дочаква","драмско","државен","државно","духовен","духовно","дълбоко","дължина","егейски","егејски","единица","еднакво","експерт","елемент","енергия","ерлајнс","ерменец","есенско","желание","жестоко","живеене","живеење","животна","животно","жизнено","забавен","забавно","забрана","забрани","завзема","завземе","завраќа","завръща","загледа","заговор","загрози","задвижи","задолжи","задушен","задушно","задължи","задържа","задържи","заклучи","заключи","законик","законов","закуска","заменик","замесен","замесно","западен","западне","западно","заплата","заплаха","заплени","заповед","заразен","заразно","зарасне","зарасте","заслужи","засмета","засмята","застава","застане","застапи","застъпи","затвара","затваря","затвори","затврди","заштита","заштити","защитен","защитно","зголеми","значење","идеален","идеално","избегне","изборен","изборно","избрано","избягва","извесно","извести","извзема","извземе","извршен","извърши","изгледа","изгради","изгубва","издаден","издание","издолжи","издължи","издържи","изиграе","изказва","изложба","измамен","измамно","изнаоѓа","изнајде","изпадне","изплаща","изправи","изправя","изпрати","изпраща","изтегли","изтегля","източен","източно","изтъква","изтъкне","илјаден","индивид","инерция","инженер","интервю","интерес","интимен","интимно","иракски","ирански","испадне","исплата","исплаќа","исправи","испрати","испраќа","истакне","история","источно","кабинет","кампања","канцлер","капитал","кариера","католик","ключово","колежка","колешка","команда","комесар","комисар","комисия","комитет","конгрес","конечно","контакт","контрол","концерт","корисно","користи","кралски","крепост","критика","критски","култура","кюрдски","легален","легално","лечение","личност","локален","локално","лъжливо","мазнина","масовно","медийно","месечно","меѓутоа","милиция","минутен","минутно","мировно","мислење","младост","мобилен","мобилно","модерен","модерно","можност","мозайка","морален","морално","мощност","музичко","набавка","навежда","навлезе","навлиза","наводно","навреди","навърши","нагласи","наглася","нагледа","награда","наддава","наддаде","надежда","надзема","надземе","надлаже","надлъже","надмине","назначи","наказва","намален","намерен","намерно","наместо","нападне","наплаща","наплаќа","напуска","напусне","напушта","напушти","напълно","наредба","нарежда","народен","народно","населен","насилие","наскоро","наследи","насочен","настава","настане","настапи","настоящ","настъпи","насърчи","натъкне","научник","наштети","најдено","најпрво","небесен","небесно","невинен","невинно","некаков","некогаш","неколку","немирен","немирно","неруски","несреќа","неуспех","нечисто","никаков","никакъв","никогаш","николко","николку","ноември","някакъв","няколко","обвземе","обвинен","обгледа","обедини","обидува","обмисля","обседне","обслужи","обсъжда","обхваща","објасни","огромен","огромно","одбрана","одвраќа","одгледа","одговор","одделно","односно","одобрен","одредба","одржано","окружно","окръжно","опишува","опседне","опслужи","општина","основен","основно","особено","осознае","оставка","остаток","остатък","осудено","осудува","осъдено","осъзнае","отбрана","отворен","отвръща","отгледа","отговор","отделен","отделно","отколку","открито","отложен","отпадне","отпадък","отплаща","отплаќа","отправи","отпушти","отровен","отровно","отседне","отслужи","отстапи","отстъпи","оттогаш","охрабри","очекува","пазарно","паричен","парично","партиен","партија","партнер","пасивен","пасивно","паспорт","пензија","петиция","печалба","планина","планира","плащане","плаќање","победен","победно","повелба","повлече","повлияе","повраќа","повреда","повръща","повтаря","повтори","повярва","погледа","подаден","подбуди","поддава","поддаде","поддржи","поделба","поделен","подкупи","подлаже","подлъже","поднесе","подобен","подобно","подобри","подоцна","подпише","подходи","подържи","подялба","поетско","позволи","познато","поискан","показан","показва","поканен","покойно","покрене","покрива","политик","полицай","полиция","положба","помогне","поништи","попадне","поправи","попречи","поръчва","поръчка","поседне","послужи","посочва","посочен","поставя","постапи","постъпи","поткупи","потпише","потрага","потреба","потресе","пофалба","похвали","почетен","почетно","почеток","почнува","появява","појадок","правене","правење","правило","празник","прашање","прашина","првично","пребара","преглед","предава","предаде","предвид","предмет","прекине","прекрши","прекупи","прелаже","прелъже","премиер","премине","пренася","пренесе","престои","престой","престој","пресуди","прецени","привиди","приврши","придава","придаде","придржи","признае","призове","прииска","прикрие","примена","принцип","природа","присака","пристап","присъди","притвор","причака","причека","причина","проблем","провери","продава","продаде","продукт","промени","променя","пропише","простор","протест","противи","проходи","процени","процент","прошири","работен","работно","равнище","разбира","раздава","раздаде","раздели","разкаже","разкрие","разлика","размена","разреши","разшири","рамково","рангира","раскаже","раскрие","реакция","ревизия","редовен","редовно","режисер","резерва","рейтинг","религия","реформа","решаващ","рејтинг","романец","ротация","румънец","санкция","сблъска","светско","свечено","свещено","свински","свобода","свързан","свързва","северен","северно","сегашен","сегашно","седиште","седмица","сезонно","секаков","секција","сигурно","система","скандал","скопски","скромен","скромно","следене","следење","слобода","сложено","слушане","слушање","смелост","сменува","смъртно","снимане","снимање","согласи","согледа","создава","солиден","солидно","сомнева","соочува","сопруга","соседно","сојузно","спечели","сподели","спомага","спортен","спортно","средина","сръбски","ставање","станица","станува","станция","стапало","стапува","столица","стотица","страшен","страшно","студено","студент","стъпало","судрува","судство","събитие","съвзема","съвземе","съгласи","съгледа","съдебен","съдебна","съдебно","съдържа","създава","съмнява","съпруга","съседен","съседно","съюзник","тврдење","тековно","телеком","телесен","телесно","телефон","тензија","тепърва","течение","типичен","типично","толкова","тортура","точност","тревник","тренира","третина","третман","трипати","туризам","туризъм","турнеја","търсено","уапсено","убедува","убежище","убиство","уведоми","увеличи","уверува","уверява","угледен","угледно","удостои","укажува","укинува","уметник","унищожи","упатува","управно","условен","условно","успешен","успешно","уставен","уставно","утрешен","утрешно","участва","учесник","училище","фабрика","фамозен","фамозно","фатален","фатално","фигурно","филмово","филмско","финален","финално","финанси","фракция","френски","функция","хиляден","целосно","цивилен","цивилно","честита","честити","четврти","чудесен","чудесно","чужбина","шведски","шиитски","школски","явности","јавност","јануари"],"8":["аврамски","автократ","авторски","агенција","аеробика","аеродром","академия","актуелен","актуелно","акционен","аландски","албански","алегория","алергија","алжирски","алијанса","амандман","амбасада","амбиција","амброзия","амнистия","анархија","анатомия","англиски","анимация","анонимен","анонимно","антитеза","априлски","армейски","архаизам","архаизъм","атлански","бабунски","баварски","бактерия","балетско","банатски","биология","биохимия","битолски","болонски","болоњски","бомбашки","бомбашко","босански","боснески","ботаника","бошњачки","братство","бригадно","брутален","брутално","бугарски","буџетски","българин","бюджетен","вакуфски","вакъфски","вербален","вербално","вероятен","вероятно","винарски","вклучено","вклучува","включено","владеене","владеење","влажност","влијание","внимание","воведува","возвраќа","воздушен","воздушно","вонреден","вонредно","вооружен","восприма","вредност","временен","временно","всичкият","всушност","всъщност","всякакъв","вчерашен","вчерашно","възвръща","въздушен","въздушно","въздържи","възможен","възможно","въоръжен","върховен","върховно","вътрешен","вътрешно","гаранция","глобален","глобално","голански","големина","градежен","градежно","граничен","гранично","гробница","движение","действие","декември","десетица","дефинира","дефлация","деценија","династия","дипломат","директен","директно","директор","добивање","доведува","доверлив","доделено","доделува","дозволен","доизкаже","доизрече","доискаже","докажува","документ","донесува","дообясни","допишува","допокрие","дособере","дособира","достигне","досъбере","досъбира","дочекува","дунавски","държавен","държавно","еволюция","еврейски","еврејски","европски","единство","еколошко","енергиен","енергија","естонски","ефикасен","ефикасно","еърлайнс","женевски","забранен","забрзува","завршено","завршува","завършва","завършен","загинува","загрижен","заделено","задржува","задушено","заизлиза","закажано","заканува","заклетва","заключва","законово","законско","закупува","заменува","заминава","заминува","занимава","запознае","заразено","заседава","застраши","застъпва","затворен","затвърди","заштитно","земунски","земјиште","значение","избиране","избирање","избрбори","известен","известно","извештај","извршено","извршува","извършва","извършен","изглежда","изгражда","изгубува","издаване","издавање","издадено","издигане","издигање","изкупува","изкуство","излегува","измамено","изменува","измирски","изнамери","изнамира","изнесува","изолация","изостава","изостави","изостане","използва","изпратен","изпълнен","изразува","изразява","изутрина","изчезнал","имигрант","имунитет","индийски","инерција","институт","интервју","интернет","инфекция","инфлация","инцидент","искажува","искупува","ислямски","истекува","историја","кампания","канадски","канарски","кандидат","канцелар","карибски","картичка","катарски","качество","квалитет","килограм","кипърски","коалиция","козарски","колекция","коментар","комисија","комитски","компания","конзулат","контрола","корейски","корекция","корисник","користен","користно","корупция","косовски","критерий","критичен","критично","кубински","културен","културно","купуване","купување","латински","лекарски","лекуване","лекување","либийски","ливански","лидерски","литовски","лишаване","лобиране","лобирање","локација","мандатор","материал","медицина","месечина","миграция","микенски","милански","милионен","милитант","милиција","милярден","министер","министър","минойски","мировник","моментен","моментно","муслиман","мутиране","мутирање","набрбори","наведува","наглежда","надвзема","надвземе","надежден","надеждно","надзорен","надзорно","надлежен","надлежно","наистина","накажува","накратко","накупува","намалено","намалува","намалява","намерено","намиране","направен","напредок","напротив","наредува","наречено","нарушава","насобере","насобира","насочено","наспрема","насрочен","настоящо","настъпва","насъбере","насъбира","нафтовод","началник","недвижно","неодамна","непредък","нервозен","нервозно","нетурски","неуморен","неуморно","номадски","норвежки","нормален","нормално","обвинено","обвинето","обвинува","обвинява","обиколен","обиколка","обиколно","обраќање","обучение","общество","общински","обяснява","овозможи","оглавява","одвојува","одложено","одложува","однесува","одобрено","одобрува","одобрява","одржливо","океански","октомври","окупация","олеснува","опасност","оператор","операция","оповести","опозиция","определи","оптимист","освободи","освојува","ослободи","останало","отваряне","отворање","отворено","откриено","откупува","отлагане","отложено","отпатува","отпочива","отпочине","отпътува","отстрани","отстъпва","отсуство","оттогава","отхвърли","охридски","очевидно","паметник","панамски","панорама","парников","партийно","партиско","партньор","патлиџан","персонал","петиција","пилотски","пиратски","победено","побрбори","поверува","повикува","повлијае","поврзано","поврзува","повторен","повторно","погодува","погрешен","погрешно","подадено","подбужда","подвижен","подвижно","подготви","подготвя","поддршка","поделено","подземен","подземно","подкрепи","подкрепя","подписан","подписва","подрежда","подтиква","подхожда","поединец","поетично","позабрза","позадржи","позасили","позволен","поздрави","поискано","покажано","покажува","показано","поканено","покането","поканува","полагане","полагање","политика","полицаец","полиција","половина","получава","поминува","помошник","помощник","понамали","понатаму","пообясни","пооткрие","попомине","порачува","посакано","посветен","поседува","посетува","посещава","послание","посланик","последен","последно","пособере","посочено","посочува","поспадне","постапка","постигне","постојно","постъпва","постъпка","посъбере","потребно","поттикне","поускори","пофалува","починато","починува","почитува","појавува","правилен","правилно","превземе","превозно","прегледа","преговор","предаден","предвиди","предводи","предстои","премахва","премахне","премногу","преносен","преносно","преправи","преседан","пресечен","пресечно","пресмета","пресмята","пресреща","престава","престане","престапи","престъпи","претстои","претърси","преценка","прецизен","прецизно","приближи","приватно","привлече","привърши","придвижи","придойде","придонес","придојде","придружи","придържи","приемане","приемлив","признава","приклучи","припадне","приправи","природен","природно","приседне","пристава","пристане","пристапи","присъжда","проверка","прогледа","програма","продажба","продажен","продажно","продолжи","продължи","проектил","производ","прокурор","пролетен","пролетно","пропадне","прослави","протокол","проценка","публичен","публично","работник","разгледа","разговор","разгръща","разгърне","раздвижи","раздолжи","раздължи","разказва","различен","различно","разпадне","разплата","разправи","разрушен","разселен","разтърси","разубеди","разузнае","рамковно","раселено","распадне","расправа","расправи","реакција","реалност","ревизија","редакция","режисьор","резервен","резервно","резовски","резултат","рекламен","рекламно","рекорден","рекордно","религија","ресторан","решаване","решаващо","решавање","решеност","решимост","рибарски","ротација","румънски","санкција","светлост","световен","световно","свидетел","свободен","свободно","свързано","седалище","сезонско","секретар","сенатски","сериозен","сериозно","синдикат","сирийски","системно","ситуация","скулптор","следващо","слободно","словашки","службено","служебно","служител","собрание","собствен","советник","совпадне","солунски","состојба","софийски","социален","социално","сочинува","сојузник","сплитски","споменик","спомогне","споредба","спортист","спортско","справува","справяне","спречува","средство","стабилен","стабилно","стандард","стандарт","стареене","стареење","стигнува","стойност","страдање","страница","странско","судански","сунитски","сутрешен","сутрешно","сутринта","съблазън","събрание","съветник","съвпадне","създаден","съобщава","съставен","съставно","телеграф","терорист","тетовски","тибетски","тирански","товарене","товарење","трагичен","трагично","трговија","трибунал","трудност","търговия","убеждава","убийство","увеличен","уволнява","улеснява","уметност","унгарски","уништено","уништува","употреба","ускорява","утринско","участник","училиште","учредява","факултет","февруари","фестивал","финансии","финансов","фискален","фискално","фокусира","фондация","формален","формално","фракција","функција","футболен","футболно","хигиенно","хититски","хотелски","храброст","хроничен","хронично","художник","хърватин","централа","цигански","часовник","частичен","частично","четворка","четврток","четвърти","чеченски","членство","човештво","шестотен","шпионски","јавности"],"9":["абсолютно","автомобил","автономен","автономия","автономно","агресивен","агресивно","адекватен","адекватно","адреналин","академија","академско","активизам","активизъм","алегорија","алкохолик","амбасадор","амброзија","амнестија","анадолски","анархизам","анархизъм","анатолски","анатомија","английски","анестезия","анимација","анкетиран","апсолутно","арамейски","арамејски","арестуван","асоциация","аспирация","аудиенция","багдадски","бактерија","балкански","башибозук","белоруски","берлински","биологија","биохемија","блокиране","блокирање","богослужи","босненски","бостонски","бостънски","ботаничар","бразилски","британски","брокерски","бунтовник","български","валидност","вандалски","варшавски","вајарство","веројатен","вистински","вистинско","включване","влагалище","водорасли","вооружено","вработува","вселенски","възприема","въоръжено","гаранција","генерален","генерално","генерация","германски","гигантски","гласуване","говорител","годишнина","двестотен","дводневен","дводневно","двудневен","двудневно","деблокира","декорация","делегация","денонощие","деноноќие","детонация","дефлација","динамичен","динамично","династија","дискутира","доверливо","доживотно","дозволено","доизгледа","доизгради","доизказва","доколкото","дообјасни","допокрива","допринесе","доразкаже","дораскаже","досегашен","досегашно","доставува","драстичен","драстично","евакуация","еволуција","египетски","единствен","ежедневен","ежедневно","економија","економски","експертно","експлозив","експлозия","елегантен","елегантно","емиграция","енергийно","енергичен","енергично","ескалация","етнически","забранено","забрането","забранува","забранява","завършено","загребски","загрижено","загрозува","задоволно","задържано","заедничко","заклучува","заместник","запленува","започване","застанува","застапува","затваряне","затворано","затворање","затворено","затворник","затворска","заявление","зголемено","зголемува","здравство","здружение","земеделие","земјотрес","злополука","идентитет","избегнува","избирачко","избърбори","известува","извршител","извършено","изградува","издейства","издирване","изменение","изолација","изолиране","изолирање","изпланира","използван","изпратено","изпращане","изпълнено","изпълнява","израелски","изтегляне","изучаване","изучување","изчезнало","изявление","икономика","имиграция","инвестира","индикация","инертност","инспектор","интересен","интересно","инфекција","инфлација","информира","искористи","искреност","исландски","испитаник","испланира","исполнето","исполнува","испратено","испраќање","истакнува","исчезнало","кандидира","капацитет","категория","квадратно","километар","километър","клониране","клонирање","коалиција","колекција","командант","командващ","компанија","компромис","комунизам","комунизъм","конвенция","конкретен","конкретно","консензус","консенсус","контролен","контролно","корекција","коринтски","користење","корупција","кремиране","кремирање","кристален","кристално","критериум","критикува","кувейтски","легитимен","легитимно","либерален","либерално","лидерство","лондонски","мадридски","македонец","малолетен","малцинско","мартенски","материјал","медиумско","менаџмент","миграција","милионски","минимален","минимално","митология","молдовски","монголски","московски","мотивация","музикално","набърбори","навистина","навлегува","навсякъде","нагласува","наглеждан","надминава","надминува","назначено","намерение","направено","напускане","напуштање","население","насилство","наследник","насрочено","наставник","настанува","настапува","насърчава","неарабски","негативен","негативно","недвижимо","недоверба","недоверие","недоволен","недоволно","недогледа","незабавен","незабавно","независим","независно","незаконно","неизбежен","неизбежно","неколцина","нелегално","необходим","неопходно","неотдавна","неплащане","неплаќање","нередност","неуспешен","неуспешно","номинация","нуклеарно","обвинител","обединува","обединява","обелодени","образовно","обръщение","обявление","објаснува","одблокира","одговорно","одобрение","одржување","окупација","окупиране","окупирање","олимпиада","омаловажи","операција","опозиција","оптимален","оптимално","оптимизам","оптимизъм","општество","освободен","осоговски","остранява","осъществи","отбелязва","отблокира","отговорно","отколкото","отношение","отомански","отпуштува","отстапува","отсъствие","оттегляне","официален","официално","охрабрува","очигледно","панорамно","паравоено","паралелен","паралелно","парламент","патладжан","педесетти","петдесети","петстотен","пионерски","писменост","планински","планиране","планирано","планирање","пластичен","пластично","платформа","побърбори","повдигане","повлекува","повторува","подгорски","подготвен","поддржува","поддръжка","подейства","поднесува","подобрува","подобрява","подписано","подпомага","позагледа","позадържи","позатврди","позволено","позитивен","позитивно","поизправи","поисправи","покренува","политичар","полковник","положение","понавлезе","понагласи","понасърчи","пообјасни","поотстапи","поотстъпи","поохрабри","попремине","попречува","попрошири","поразшири","портпарол","посетител","посещение","последица","посолство","поставено","поставува","поставяне","постапува","постепено","постигане","постоянен","постоянно","потенциал","потерница","потпишано","потпишува","потпомага","потресува","правилник","практичен","практично","првенство","преввземе","превенция","преговара","преговаря","предаване","предавање","предадено","предвижда","предизвик","предложен","предплаща","предприет","предскаже","представи","представя","предходен","предходно","преземање","преземено","президент","преизбере","преизбира","преиздава","преиздаде","прекалено","прекинува","прекрасен","прекрасно","прекршува","прекупува","преминава","пренесува","препознае","препокрие","препорака","препорача","препоръка","препоръча","пресечено","пресретне","пресрещне","пресудува","претплаќа","претскаже","претстави","претходно","префрлено","прецедент","преценява","придонесе","приемливо","признание","призовава","прилагане","приоритет","припокрие","присуство","присъства","притежава","прифатено","прифаќање","проведено","програмно","продаване","продавање","продукция","произлезе","произлиза","произнася","произтича","променува","промовира","пропатува","пропътува","просветен","просветно","прославен","прославно","просторен","просторно","противење","процедура","проценува","проширува","радикален","радикално","разбиване","разбивање","разбиране","разбирање","разбрбори","развидели","разглежда","разговара","разговаря","разпознае","разрушено","разселено","разтърсва","разузнава","разширява","раскажува","распознае","распореди","регулация","редакција","резулюция","релативно","република","репутация","ресторант","реформско","решавајќи","рихтерова","рождество","ротациско","саксонски","самоубива","санитарен","санитарно","сараевски","сдружение","сексуален","сексуално","семейство","семејство","септември","системско","ситуација","скулптура","славянски","словенски","службеник","собствено","согласува","создавање","создадено","солидарен","солидарно","сомневање","сообраќај","соодветно","соопштува","сопостави","сопствено","соработка","сортиране","сортирање","составено","социалист","социјално","спасување","спасяване","специален","специално","спротивно","сравнение","стагнация","стимулира","стопански","страдание","странство","стратегия","структура","съвместен","съвместно","съгласява","съдейства","създаване","създадено","съобщение","съответно","съпостави","съпоставя","състезава","състояние","сътрудник","съучаства","твърдение","театарско","театрален","театрално","телевизия","телефонен","телефонно","теоретско","територия","тероризам","тероризъм","тешкотија","тракийски","транзитен","транзитно","транспорт","тридневен","тридневно","трикратен","трикратно","тристотен","търговски","уведомява","увеличава","увеличено","увереност","уверување","укинување","украински","укрепване","умереност","уметничко","унищожава","усвояване","устойчиво","учествува","федерален","федерално","федерация","финансира","финансово","фондација","формиране","формирање","фудбалско","хасковски","хигиенско","холандски","хърватски","хърватско","целокупен","целокупно","централен","централно","церемония","четворица","четвъртък","шампионат","шенгенски"]}}